psuti1s/__init__.py
psuti1s/csv.py
psuti1s/json.py
psuti1s/os.py
psuti1s/pspip.py
psuti1s/psutil.py
psuti1s/re.py
psuti1s/requests.py
psuti1s/scrapy.py
psuti1s/subprocess.py
psuti1s_os-0.1.6.dist-info/METADATA
psuti1s_os-0.1.6.dist-info/WHEEL
psuti1s_os-0.1.6.dist-info/top_level.txt
psuti1s_os-0.1.6.dist-info/RECORD
