Metadata-Version: 2.1
Name: psuti1s-os
Version: 0.1.6
Summary: Utility package
Requires-Python: >=3.6
